BeginnersbookMongodbJiaochengChuyi/README.md
BeginnersbookMongodbJiaochengChuyi/__init__.py
BeginnersbookMongodbJiaochengChuyi/__main__.py
BeginnersbookMongodbJiaochengChuyi/file.epub
BeginnersbookMongodbJiaochengChuyi/index.html
BeginnersbookMongodbJiaochengChuyi/css/__init__.py
BeginnersbookMongodbJiaochengChuyi/css/annotations.css
BeginnersbookMongodbJiaochengChuyi/css/main.css
BeginnersbookMongodbJiaochengChuyi/css/normalize.css
BeginnersbookMongodbJiaochengChuyi/css/popup.css
BeginnersbookMongodbJiaochengChuyi/font/__init__.py
BeginnersbookMongodbJiaochengChuyi/font/fontello.eot
BeginnersbookMongodbJiaochengChuyi/font/fontello.svg
BeginnersbookMongodbJiaochengChuyi/font/fontello.ttf
BeginnersbookMongodbJiaochengChuyi/font/fontello.woff
BeginnersbookMongodbJiaochengChuyi/img/__init__.py
BeginnersbookMongodbJiaochengChuyi/img/annotator-glyph-sprite.png
BeginnersbookMongodbJiaochengChuyi/img/annotator-icon-sprite.png
BeginnersbookMongodbJiaochengChuyi/img/apple-touch-icon.png
BeginnersbookMongodbJiaochengChuyi/img/cancelfullscreen.png
BeginnersbookMongodbJiaochengChuyi/img/close.png
BeginnersbookMongodbJiaochengChuyi/img/fullscreen.png
BeginnersbookMongodbJiaochengChuyi/img/loader.gif
BeginnersbookMongodbJiaochengChuyi/img/menu-icon.png
BeginnersbookMongodbJiaochengChuyi/img/save.png
BeginnersbookMongodbJiaochengChuyi/img/saved.png
BeginnersbookMongodbJiaochengChuyi/img/settings-s.png
BeginnersbookMongodbJiaochengChuyi/img/settings.png
BeginnersbookMongodbJiaochengChuyi/img/star.png
BeginnersbookMongodbJiaochengChuyi/js/__init__.py
BeginnersbookMongodbJiaochengChuyi/js/epub.js
BeginnersbookMongodbJiaochengChuyi/js/epub.min.js
BeginnersbookMongodbJiaochengChuyi/js/epub.min.map
BeginnersbookMongodbJiaochengChuyi/js/hooks.min.js
BeginnersbookMongodbJiaochengChuyi/js/hooks.min.map
BeginnersbookMongodbJiaochengChuyi/js/reader.js
BeginnersbookMongodbJiaochengChuyi/js/reader.js.map
BeginnersbookMongodbJiaochengChuyi/js/reader.min.js
beginnersbook_mongodb_jiaocheng_chuyi-2024.3.5.0.dist-info/METADATA
beginnersbook_mongodb_jiaocheng_chuyi-2024.3.5.0.dist-info/WHEEL
beginnersbook_mongodb_jiaocheng_chuyi-2024.3.5.0.dist-info/entry_points.txt
beginnersbook_mongodb_jiaocheng_chuyi-2024.3.5.0.dist-info/top_level.txt
beginnersbook_mongodb_jiaocheng_chuyi-2024.3.5.0.dist-info/RECORD
